cladeomatic/__init__.py
cladeomatic/benchmark.py
cladeomatic/constants.py
cladeomatic/create.py
cladeomatic/main.py
cladeomatic/simulate_genomes.py
cladeomatic/test.py
cladeomatic/version.py
cladeomatic/utils/__init__.py
cladeomatic/utils/jellyfish.py
cladeomatic/utils/kmerSearch.py
cladeomatic/utils/phylo_tree.py
cladeomatic/utils/seqdata.py
cladeomatic/utils/vcfhelper.py
cladeomatic/utils/visualization.py
cladeomatic-0.0.1.dist-info/LICENSE
cladeomatic-0.0.1.dist-info/METADATA
cladeomatic-0.0.1.dist-info/WHEEL
cladeomatic-0.0.1.dist-info/entry_points.txt
cladeomatic-0.0.1.dist-info/top_level.txt
cladeomatic-0.0.1.dist-info/RECORD
